<annotation>
	<folder></folder>
	<filename>Learn-the-Auslan-Alphabet_mp4-67_jpg.rf.773f0fcbfedf46ae33034ceba6f61c57.jpg</filename>
	<path>Learn-the-Auslan-Alphabet_mp4-67_jpg.rf.773f0fcbfedf46ae33034ceba6f61c57.jpg</path>
	<source>
		<database>roboflow.com</database>
	</source>
	<size>
		<width>640</width>
		<height>640</height>
		<depth>3</depth>
	</size>
	<segmented>0</segmented>
	<object>
		<name>G</name>
		<pose>Unspecified</pose>
		<truncated>0</truncated>
		<difficult>0</difficult>
		<occluded>0</occluded>
		<bndbox>
			<xmin>261</xmin>
			<xmax>387</xmax>
			<ymin>176</ymin>
			<ymax>592</ymax>
		</bndbox>
	</object>
</annotation>
